alibabacloud_farui20240628/__init__.py
alibabacloud_farui20240628/client.py
alibabacloud_farui20240628/models/__init__.py
alibabacloud_farui20240628/models/_create_text_file_advance_request.py
alibabacloud_farui20240628/models/_create_text_file_request.py
alibabacloud_farui20240628/models/_create_text_file_response.py
alibabacloud_farui20240628/models/_create_text_file_response_body.py
alibabacloud_farui20240628/models/_run_contract_extract_request.py
alibabacloud_farui20240628/models/_run_contract_extract_response.py
alibabacloud_farui20240628/models/_run_contract_extract_response_body.py
alibabacloud_farui20240628/models/_run_contract_extract_shrink_request.py
alibabacloud_farui20240628/models/_run_contract_result_generation_request.py
alibabacloud_farui20240628/models/_run_contract_result_generation_response.py
alibabacloud_farui20240628/models/_run_contract_result_generation_response_body.py
alibabacloud_farui20240628/models/_run_contract_result_generation_shrink_request.py
alibabacloud_farui20240628/models/_run_contract_rule_generation_request.py
alibabacloud_farui20240628/models/_run_contract_rule_generation_response.py
alibabacloud_farui20240628/models/_run_contract_rule_generation_response_body.py
alibabacloud_farui20240628/models/_run_contract_rule_generation_shrink_request.py
alibabacloud_farui20240628/models/_run_legal_advice_consultation_request.py
alibabacloud_farui20240628/models/_run_legal_advice_consultation_response.py
alibabacloud_farui20240628/models/_run_legal_advice_consultation_response_body.py
alibabacloud_farui20240628/models/_run_legal_advice_consultation_shrink_request.py
alibabacloud_farui20240628/models/_run_search_case_full_text_request.py
alibabacloud_farui20240628/models/_run_search_case_full_text_response.py
alibabacloud_farui20240628/models/_run_search_case_full_text_response_body.py
alibabacloud_farui20240628/models/_run_search_case_full_text_shrink_request.py
alibabacloud_farui20240628/models/_run_search_law_query_request.py
alibabacloud_farui20240628-1.3.0.dist-info/LICENSE
alibabacloud_farui20240628-1.3.0.dist-info/METADATA
alibabacloud_farui20240628-1.3.0.dist-info/WHEEL
alibabacloud_farui20240628-1.3.0.dist-info/top_level.txt
alibabacloud_farui20240628-1.3.0.dist-info/RECORD
